[
  {
    "name": "Market beta",
    "value": 0.976,
    "limit": 0.3,
    "status": "Breach"
  },
  {
    "name": "Size beta",
    "value": 0.394,
    "limit": 0.2,
    "status": "Breach"
  },
  {
    "name": "Value beta",
    "value": -0.784,
    "limit": 0.2,
    "status": "Breach"
  },
  {
    "name": "Momentum beta",
    "value": 0.784,
    "limit": 0.25,
    "status": "Breach"
  },
  {
    "name": "Rates beta",
    "value": -0.18,
    "limit": 0.2,
    "status": "Warning"
  },
  {
    "name": "Credit beta",
    "value": 1.06,
    "limit": 0.2,
    "status": "Breach"
  },
  {
    "name": "Volatility beta",
    "value": -0.976,
    "limit": 0.2,
    "status": "Breach"
  },
  {
    "name": "USD beta",
    "value": -0.31,
    "limit": 0.2,
    "status": "Breach"
  },
  {
    "name": "Commodity beta",
    "value": 0.337,
    "limit": 0.2,
    "status": "Breach"
  }
]
